nextcord/__init__.py
nextcord/__main__.py
nextcord/abc.py
nextcord/activity.py
nextcord/appinfo.py
nextcord/application_command.py
nextcord/asset.py
nextcord/audit_logs.py
nextcord/auto_moderation.py
nextcord/backoff.py
nextcord/bans.py
nextcord/bin/COPYING
nextcord/bin/libopus-0.x64.dll
nextcord/bin/libopus-0.x86.dll
nextcord/channel.py
nextcord/client.py
nextcord/colour.py
nextcord/components.py
nextcord/context_managers.py
nextcord/embeds.py
nextcord/emoji.py
nextcord/enums.py
nextcord/errors.py
nextcord/ext/application_checks/__init__.py
nextcord/ext/application_checks/core.py
nextcord/ext/application_checks/errors.py
nextcord/ext/application_checks/py.typed
nextcord/ext/commands/__init__.py
nextcord/ext/commands/_types.py
nextcord/ext/commands/bot.py
nextcord/ext/commands/cog.py
nextcord/ext/commands/context.py
nextcord/ext/commands/converter.py
nextcord/ext/commands/cooldowns.py
nextcord/ext/commands/core.py
nextcord/ext/commands/errors.py
nextcord/ext/commands/flags.py
nextcord/ext/commands/help.py
nextcord/ext/commands/py.typed
nextcord/ext/commands/view.py
nextcord/ext/slash_utils/__init__.py
nextcord/ext/slash_utils/py.typed
nextcord/ext/slash_utils/slash.py
nextcord/ext/tasks/__init__.py
nextcord/ext/tasks/py.typed
nextcord/file.py
nextcord/flags.py
nextcord/gateway.py
nextcord/guild.py
nextcord/guild_preview.py
nextcord/http.py
nextcord/integrations.py
nextcord/interactions.py
nextcord/invite.py
nextcord/iterators.py
nextcord/member.py
nextcord/mentions.py
nextcord/message.py
nextcord/mixins.py
nextcord/object.py
nextcord/oggparse.py
nextcord/opus.py
nextcord/partial_emoji.py
nextcord/permissions.py
nextcord/player.py
nextcord/py.typed
nextcord/raw_models.py
nextcord/reaction.py
nextcord/role.py
nextcord/role_connections.py
nextcord/scheduled_events.py
nextcord/shard.py
nextcord/stage_instance.py
nextcord/state.py
nextcord/sticker.py
nextcord/team.py
nextcord/template.py
nextcord/threads.py
nextcord/types/__init__.py
nextcord/types/activity.py
nextcord-3.0.1.dist-info/LICENSE
nextcord-3.0.1.dist-info/METADATA
nextcord-3.0.1.dist-info/WHEEL
nextcord-3.0.1.dist-info/RECORD
